[
  {
    "version": "main",
    "url": "https://DiamondLightSource.github.io/i22-bluesky/main/"
  },
  {
    "version": "add-compliance-tests",
    "url": "https://DiamondLightSource.github.io/i22-bluesky/add-compliance-tests/"
  },
  {
    "version": "comment-out-slits4",
    "url": "https://DiamondLightSource.github.io/i22-bluesky/comment-out-slits4/"
  },
  {
    "version": "dependabot_github_actions_codecov_codecov-action-4",
    "url": "https://DiamondLightSource.github.io/i22-bluesky/dependabot_github_actions_codecov_codecov-action-4/"
  },
  {
    "version": "fix-stopflow",
    "url": "https://DiamondLightSource.github.io/i22-bluesky/fix-stopflow/"
  },
  {
    "version": "fix-stopflow-config",
    "url": "https://DiamondLightSource.github.io/i22-bluesky/fix-stopflow-config/"
  },
  {
    "version": "format-stopflow",
    "url": "https://DiamondLightSource.github.io/i22-bluesky/format-stopflow/"
  },
  {
    "version": "remove-3.9",
    "url": "https://DiamondLightSource.github.io/i22-bluesky/remove-3.9/"
  },
  {
    "version": "remove-boilerplate-tests",
    "url": "https://DiamondLightSource.github.io/i22-bluesky/remove-boilerplate-tests/"
  }
]